gfw_api_python_client-3.0.0.dist-info/licenses/LICENSE
gfwapiclient/__init__.py
gfwapiclient/__version__.py
gfwapiclient/base/__init__.py
gfwapiclient/base/models.py
gfwapiclient/client/__init__.py
gfwapiclient/client/client.py
gfwapiclient/exceptions/__init__.py
gfwapiclient/exceptions/base.py
gfwapiclient/exceptions/client.py
gfwapiclient/exceptions/http.py
gfwapiclient/exceptions/validation.py
gfwapiclient/http/__init__.py
gfwapiclient/http/client.py
gfwapiclient/http/resources.py
gfwapiclient/http/endpoints/__init__.py
gfwapiclient/http/endpoints/abc.py
gfwapiclient/http/endpoints/base.py
gfwapiclient/http/endpoints/get.py
gfwapiclient/http/endpoints/post.py
gfwapiclient/http/models/__init__.py
gfwapiclient/http/models/request.py
gfwapiclient/http/models/response.py
gfwapiclient/resources/__init__.py
gfwapiclient/resources/datasets/__init__.py
gfwapiclient/resources/events/__init__.py
gfwapiclient/resources/events/resources.py
gfwapiclient/resources/events/base/__init__.py
gfwapiclient/resources/events/base/models/__init__.py
gfwapiclient/resources/events/base/models/request.py
gfwapiclient/resources/events/base/models/response.py
gfwapiclient/resources/events/detail/__init__.py
gfwapiclient/resources/events/detail/endpoints.py
gfwapiclient/resources/events/detail/models/__init__.py
gfwapiclient/resources/events/detail/models/request.py
gfwapiclient/resources/events/detail/models/response.py
gfwapiclient/resources/events/list/__init__.py
gfwapiclient/resources/events/list/endpoints.py
gfwapiclient/resources/events/list/models/__init__.py
gfwapiclient/resources/events/list/models/request.py
gfwapiclient/resources/events/list/models/response.py
gfwapiclient/resources/events/stats/__init__.py
gfwapiclient/resources/events/stats/endpoints.py
gfwapiclient/resources/events/stats/models/__init__.py
gfwapiclient/resources/events/stats/models/request.py
gfwapiclient/resources/events/stats/models/response.py
gfwapiclient/resources/fourwings/__init__.py
gfwapiclient/resources/fourwings/resources.py
gfw_api_python_client-3.0.0.dist-info/METADATA
gfw_api_python_client-3.0.0.dist-info/WHEEL
gfw_api_python_client-3.0.0.dist-info/top_level.txt
gfw_api_python_client-3.0.0.dist-info/RECORD
