Metadata-Version: 2.4
Name: gfw-api-python-client
Version: 3.0.0
Summary: Python package for accessing data from Global Fishing Watch APIs.
Author-email: Global Fishing Watch <apis@globalfishingwatch.org>
Maintainer-email: Global Fishing Watch <apis@globalfishingwatch.org>
License: Apache License 2.0
Project-URL: Homepage, https://github.com/GlobalFishingWatch/gfw-api-python-client
Project-URL: Documentation, https://globalfishingwatch.github.io/gfw-api-python-client/
Project-URL: Changelog, https://github.com/GlobalFishingWatch/gfw-api-python-client/blob/main/CHANGELOG.md
Project-URL: Repository, https://github.com/GlobalFishingWatch/gfw-api-python-client
Project-URL: Issues, https://github.com/GlobalFishingWatch/gfw-api-python-client/issues
Keywords: global fishing watch,gfw,apis,api client,fishing data,satellite data,vessel data,marine data,geospatial data,ocean monitoring,marine research,marine conservation,environmental research,ocean sustainability,ais,vms
Classifier: Development Status :: 4 - Beta
Classifier: Environment :: Console
Classifier: Framework :: Pydantic
Classifier: Framework :: Pydantic :: 2
Classifier: Intended Audience :: Developers
Classifier: Intended Audience :: Science/Research
Classifier: License :: OSI Approved :: Apache Software License
Classifier: Natural Language :: English
Classifier: Operating System :: OS Independent
Classifier: Programming Language :: Python
Classifier: Programming Language :: Python :: 3
Classifier: Programming Language :: Python :: 3 :: Only
Classifier: Programming Language :: Python :: 3.12
Classifier: Programming Language :: Python :: 3.13
Classifier: Programming Language :: Python :: 3.14
Classifier: Topic :: Software Development
Classifier: Topic :: Software Development :: Libraries
Classifier: Topic :: Software Development :: Libraries :: Python Modules
Classifier: Topic :: Utilities
Classifier: Topic :: Scientific/Engineering
Classifier: Typing :: Typed
Requires-Python: >=3.12
License-File: LICENSE
Requires-Dist: httpx~=0.28
Requires-Dist: pydantic~=2.10
Requires-Dist: pydantic-settings~=2.8
Requires-Dist: mapbox-vector-tile~=2.1
Requires-Dist: pandas~=2.2
Requires-Dist: geopandas~=1.0
Provides-Extra: lint
Requires-Dist: black>=25.1.0; extra == "lint"
Requires-Dist: isort>=6.0.1; extra == "lint"
Requires-Dist: mypy>=1.15.0; extra == "lint"
Requires-Dist: pydocstyle>=6.3.0; extra == "lint"
Requires-Dist: ruff>=0.11.2; extra == "lint"
Requires-Dist: codespell[toml]>=2.4.1; extra == "lint"
Provides-Extra: test
Requires-Dist: pytest>=8.3.5; extra == "test"
Requires-Dist: pytest-asyncio>=0.26.0; extra == "test"
Requires-Dist: pytest-cov>=6.0.0; extra == "test"
Requires-Dist: pytest-mock>=3.14.0; extra == "test"
Requires-Dist: pytest-xdist>=3.6.1; extra == "test"
Requires-Dist: pytest-timeout>=2.3.1; extra == "test"
Requires-Dist: coverage[toml]>=7.7.1; extra == "test"
Requires-Dist: respx>=0.22.0; extra == "test"
Provides-Extra: dev
Requires-Dist: commitizen>=4.4.1; extra == "dev"
Requires-Dist: pre-commit>=4.2.0; extra == "dev"
Requires-Dist: pip-audit>=2.8.0; extra == "dev"
Provides-Extra: build
Requires-Dist: build>=1.2.2; extra == "build"
Requires-Dist: setuptools>=78.1.0; extra == "build"
Requires-Dist: twine>=6.1.0; extra == "build"
Provides-Extra: docs
Requires-Dist: sphinx>=8.2.3; extra == "docs"
Requires-Dist: furo>=2024.8.6; extra == "docs"
Requires-Dist: myst-parser>=4.0.1; extra == "docs"
Requires-Dist: myst-nb>=1.2.0; extra == "docs"
Requires-Dist: sphinx-copybutton>=0.5.2; extra == "docs"
Requires-Dist: sphinx-autobuild>=2024.10.3; extra == "docs"
Requires-Dist: sphinx-inline-tabs>=2023.4.21; extra == "docs"
Requires-Dist: sphinx-autodoc2>=0.5.0; extra == "docs"
Provides-Extra: notebooks
Requires-Dist: ipykernel>=6.29.5; extra == "notebooks"
Requires-Dist: ipython>=9.0.2; extra == "notebooks"
Requires-Dist: jupyterlab>=4.3.6; extra == "notebooks"
Requires-Dist: watermark>=2.5.0; extra == "notebooks"
Dynamic: license-file
